MANIFEST.in
bootstrap.py
buildout.cfg
setup.cfg
setup.py
src/COPYING
src/ChangeLog
src/README
src/pyrtm.egg-info/PKG-INFO
src/pyrtm.egg-info/SOURCES.txt
src/pyrtm.egg-info/dependency_links.txt
src/pyrtm.egg-info/entry_points.txt
src/pyrtm.egg-info/requires.txt
src/pyrtm.egg-info/top_level.txt
src/rtm/__init__.py
src/rtm/consts.py
src/rtm/rtm.py
src/rtm/samples/__init__.py
src/rtm/samples/app.py
src/rtm/tests/test_pep8.py
src/rtm/tests/test_rtm_object.py