Metadata-Version: 1.0
Name: pyrtm
Version: 0.4.1
Summary: Remember The Milk API
Home-page: http://bitbucket.org/srid/pyrtm/
Author: Sridhar Ratnakumar
Author-email: pyrtm@srid.name
License: MIT License
Platform: UNKNOWN
Classifier: Environment :: Web Environment
Classifier: Development Status :: 4 - Beta
Classifier: Intended Audience :: Developers
Classifier: License :: OSI Approved :: MIT License
Classifier: Operating System :: OS Independent
Classifier: Programming Language :: Python
Classifier: Programming Language :: Python :: 3
Classifier: Topic :: Internet
